Assignment/Assignment 3/Assignment_3/ALU.v
module alu(instruction, regA, regB, result, flags);
	input[31:0] instruction;
	input[31:0] regA,regB; 
	output[31:0] result;
	output[2:0] flags; 

	reg[5:0] opcode, func; // store the operator code and the function code
	reg[31:0] rd; // store the computing result
	reg[31:0] rs,rt; //store the operator number
	reg[5:0] shamt;
	reg[15:0] imm;
	reg[2:0] flags;
	reg[31:0] temp;
	reg[31:0] tempA;
	reg[31:0] tempB;
	always @ (*)
		begin
		tempA = regA;
		tempB = regB;
		opcode = instruction[31:26];
		func = instruction[5:0];
		flags = 3'b000;
		if(instruction[20:16]=={5'b0})
			begin
			temp = tempA;
			tempA = tempB;
			tempB = temp;
			end
		case(opcode)
		6'b000000:
			begin
				case(func)

					//add
					6'b100000:
						begin
							rs = tempA;
							rt = tempB;
							rd = rs + rt;
							if({rs[31],rt[31],rd[31]}=={3'b001}||{rs[31],rt[31],rd[31]}=={3'b110})
								flags[0] = 1;
							else 
								flags[0] = 0;
							
						end

					//addu
					6'b100001:
						begin
							rs = tempA;
							rt = tempB;
							rd = rs + rt;

						end

					//sub
					6'b100010:
						begin
							rs = tempA;
							rt = tempB;
							rd = tempA - tempB;
							if({rs[31],rt[31],rd[31]}=={3'b011}||{rs[31],rt[31],rd[31]}=={3'b100})
								flags[0] = 1;
							else
								flags[0] = 0;
						end

					//subu
					6'b100011:
						begin
							rs = tempA;
							rt = tempB;
							rd = tempA - tempB;
						end

					//and
					6'b100100:
						begin
							rs = tempA;
							rt = tempB;
							rd = rs & rt;
						end

					//nor
					6'b100111:
						begin
							rs = tempA;
							rt = tempB;
							rd = ~(rs | rt);
						end 	

                    //or
					6'b100101:
						begin
							rs = tempA;
							rt = tempB;
							rd = rs | rt;
						end		
					
					//xor
					6'b100110:
						begin
							rs = tempA;
							rt = tempB;
							rd = rs ^ rt;
						end		
					
					//slt
					6'b101010:
						begin
							rs = tempA;
							rt = tempB;
							rd = rs - rt;
							flags[1] = rd[31];  
						end

					//sltu
					6'b101011:
						begin
							rs = tempA;
							rt = tempB;
							rd = rs - rt;
							flags[1] = (rs<rt);
						end

					//sll
					6'b000000:
						begin
							rt = tempB;
							shamt = instruction[10:6];
							rd = rt << shamt;
						end
					
					//sllv
					6'b000100:
						begin
							rs = tempA;
							rt = tempB;
							rd = rt << rs;
						end
							
					//srl
					6'b000010:
						begin
							rt = tempB;
							shamt = instruction[10:6];
							rd = rt >> shamt;
						end

					//srlv
					6'b000110:
						begin
							rs = tempA;
							rt = tempB;
							rd = rt >> rs;
						end

					//sra
					6'b000011:
						begin
							rt = tempB;
							shamt = instruction[10:6];
							rd = rt >>> shamt;
						end

					//srav
					6'b000111:
						begin
							rs = tempA;
							rt = tempB;
							rd = rt >>> rs;
						end

					endcase
				end
			
			//addi
			6'b001000:
				begin
					rs = tempA;
					imm = instruction[15:0];
					if(imm[15] == 1'b1)
					     rd = rs + {16'b1,imm};
					
					else 
					     rd = rs + {16'b0,imm};
					
					if({rs[31],rd[31]}=={2'b01} || {rs[31],rd[31]} == {2'b10})
						flags[0] = 1;
					else 
						flags[0] = 0;
				end

			//addiu
			6'b001001:
				begin
					rs = tempA;
					imm = instruction[15:0];
					rd = rs + {16'b0,imm};

				end

			//andi
			6'b001100:
				begin
					rs = tempA;
					imm = instruction[15:0];
					rd = rs & {16'b0,imm};
				end

			//beq
			6'b000100:
				begin
					rs = tempA;
					rt = tempB;
					rd = rs - rt;
					if(rd=={32'b0})
						flags[2] = 1;
					else
						flags[2] = 0;
				end

			//bne
			6'b000101:
				begin
					rs = tempA;
					rt = tempB;
					rd = rs - rt;
					if(rd=={32'b0})
						flags[2] = 1;
					else
						flags[2] = 0;
				end
			
			//ori
			6'b001101:
				begin
					rs = tempA;
					imm = instruction[15:0];
					rd = rs | {16'b0,imm};
				end	

			//xori
			6'b001110:
				begin
					rs = tempA;
					imm = instruction[15:0];
					rd = rs ^ {16'b0,imm};
				end

			//slti
			6'b001010:
				begin
					rs = tempA;
					imm = instruction[15:0];
					if (imm[15] == 1'b0)
						rd = rs - {16'b0,imm};
					else 
						rd = rs - {16'b1,imm};
					flags[1] = rd[31];
				end

			//sltiu
			6'b001011:
				begin
					rs = tempA;
					imm = instruction[15:0];
					rd = rs - {16'b0,imm};
					flags[1] = (rs<{16'b0,imm});
				end

			//lw
			6'b100011:
				begin
					rs = tempA;
					imm = instruction[15:0];
					if (imm[15] == 1'b0)
					rd = rs + {16'b0,imm};
					
					else 
					rd = rs + {16'b1,imm};
					
					
				end				

			//sw
			6'b101011:
				begin
					rs = tempA;
					imm = instruction[15:0];
					if (imm[15] == 1'b0)
					rd = rs + {16'b0,imm};
					
					else 
					rd = rs + {16'b1,imm};
					
				
				end
			
			endcase
		end
	
	assign result = rd[31:0];

endmodule

Assignment/Assignment 3/temp/test_alu.v
`timescale 1ns/1ps

module test();
reg  [31:0] instruction;
reg  [31:0] regA;
reg  [31:0] regB;
wire [31:0] result;
wire [2:0] flags;

  initial begin
    $dumpfile("test.vcd");
    $dumpvars;
  end

  initial begin
	$display("\n                                   initialize");
	$monitor("instruction = 32'h%h, regA = 32'h%h, regB = 32'h%h, result = 32'h%h, flags = 3'b%b",instruction,regA,regB,result,flags);
        instruction = 32'b0;
        regA = 32'b0; 
        regB = 32'b0;
        #500
	$display("\n                                   for R Type");
	$display("\n                                   format is");
	$display("\n                      instruction:regA:regB:result:flags");
	$display("\n                                add overflow test");
        instruction = 32'h00200020;   // testing for add overflow
        regA = 32'h7FFFFFFF;
        regB = 32'h00000006;
        #100
	$display("\n                                add normal test");
	instruction = 32'h00010020;   // testing for add normal
	regA = 32'h00000001;
	regB = 32'h00000002;
	#100
	$display("\n                                sub overflow test");
        instruction = 32'h00010022;   // testing for sub overflow
        regA = 32'h7FFFFFFF;
        regB = 32'hFFFFFFFF;
	#100
	$display("\n                                sub normal test");
	instruction = 32'h00010022;   // testing for sub normal
	regA = 32'h00000004;
	regB = 32'h00000003;
	#100
	$display("\n                                  addu test");
	instruction = 32'h00200021;   // testing for addu 
	regA = 32'h7FFFFFFF;
	regB = 32'h00000006;
	#100 
	$display("\n                                  subu test");
	instruction = 32'h00010023;   // testing for subu
	regA = 32'h7FFFFFFF;
	regB = 32'hFFFFFFFF;
	#100
	$display("\n                                  and test");
	instruction = 32'h00010024;   // testing for and
	regA = 32'hFFFFFFFF;
	regB = 32'h00000001;
	#100
	$display("\n                                   or test");
	instruction = 32'h00200025;   // testing for or
	regA = 32'h00000000;
	regB = 32'h00000001;
	#100
	$display("\n                                  xor test");
	instruction = 32'h00200026;  // testing for xor
	regA = 32'hFFFFFFFF;
	regB = 32'h0000000F;
	#100
	$display("\n                                  nor test");
	instruction = 32'h00200027;  //testing for nor
	regA = 32'h00000000;
	regB = 32'hFFFFFFFF;
	#100
	$display("\n                             slt test(negative)");
	instruction = 32'h0001002A;  // testing for slt
	regA = 32'h00000000;
	regB = 32'h00000001;
	#100
	$display("\n                          slt test(non-negative)");
	instruction = 32'h0001002A;
	regA = 32'h00000001;
	regB = 32'h00000000;
	#100
	$display("\n                           sltu test(negative)");
	instruction = 32'h0001002B;  // testing for sltu
	regA = 32'h00000000;
	regB = 32'hFFFFFFFF;
	#100
	$display("\n                                sltu test");
	instruction = 32'h0001002B;  // testing for sltu
	regA = 32'hFFFFFFFF;
	regB = 32'hFFFFFFFE;
	#100
	$display("\n                                sll test");
	instruction = 32'h00010280;  // testing for sll (10)
	regA = 32'h00000000;
	regB = 32'h00000001;
	#100
	$display("\n                                srl test");
	instruction = 32'h00010282;  //testing for srl(10)
	regA = 32'h00000000;
	regB = 32'hF0000000;
	#100
        $display("\n                                sllv test");
	instruction = 32'h00010004; //testing for sllv
	regA = 32'h00000010;
	regB = 32'h00000001;
	#100
	$display("\n                                srlv test");
	instruction = 32'h00010006; // testing for srlv
	regA = 32'h00000004;
	regB = 32'h00000100;
	#100
	$display("\n                                srav test");
	instruction = 32'h00010007; // testing for srav
	regA = 32'h00000001;
	regB = 32'h00000100;
	#100
	$display("\n                                sra test");
	instruction = 32'h00010083; // testing for sra
	regA = 32'h00000000;
	regB = 32'h10000000;
	#100
	$display("\n                                         for I Type");
	$display("\n                                         format is");
	$display("\n                        instruction:regA:regB:immediate:result:flags");
	$monitor("instruction = 32'h%h, regA = 32'h%h, regB = 32'h%h, immediate = 16'b%b, result = 32'h%h, flags = 3'b%b",instruction,regA,regB,instruction[15:0],result,flags);
	$display("\n                                         addi test");
	instruction = 32'h20200001;  // testing for addi
	regA = 32'h00000001;
	regB = 32'h00000000;
	#100
	$display("\n                                     addi test(overflow)");
	instruction = 32'h20200101;  // testing for addi
	regA = 32'hFFFFFFFF;
	regB = 32'hFFFFFFFF;
	#100
	$display("\n                                        andi test");
	instruction = 32'h30010001;  // testing for andi
	regA = 32'hFFFFFFFF;
	regB = 32'h00000000;
	#100
	$display("\n                                        addiu test");
	instruction = 32'h22018001;  //testing for addiu
	regA = 32'h00000001;
	regB = 32'h00000000;
	#100
	$display("\n                                         ori test");
	instruction = 32'h32010001; //testing for ori
	regA = 32'h00000010;
	regB = 32'h00000000;
	#100
	$display("\n                                        xori test");
	instruction = 32'h38010001; //testing for xori
	regA = 32'h00000001;
	regB = 32'h00000000;
	#100
	$display("\n                                   slti test(negative)");
	instruction = 32'h28010001; //testing for slti
	regA = 32'h00000000;
	regB = 32'h00000000;
	#100
	$display("\n                                        slti test");
	instruction = 32'h28010000; //testing for slti
	regA = 32'h00000001;
	regB = 32'h00000000;
	#100
	$display("\n                                     beq test(zero)");
	instruction = 32'h10010001; //testing for beq
	regA = 32'h00000001;
	regB = 32'h00000001;
	#100
	$display("\n                                   beq test(non-zero)");
	instruction = 32'h10010001; //testing for beq
	regA = 32'h00000000;
	regB = 32'h00000001;
	#100
	$display("\n                                   bne test(non-zero)");
	instruction = 32'h14010001; //testing for bne
	regA = 32'h00000001;
	regB = 32'h00000000;
	#100
	$display("\n                                     bne test(zero)");
	instruction = 32'h14010001; //testing for bne
	regA = 32'h00000001;
	regB = 32'h00000001;
	#100
	$display("\n                                  sltiu test(negative)");
	instruction = 32'h2C010010; //testing for sltiu
	regA = 32'h00000001;
	regB = 32'h00000000;
	#100
	$display("\n                                sltiu test(non-negative)");
	instruction = 32'h2C010010; //testing for sltiu
	regA = 32'h00000100;
	regB = 32'h00000000;
	#100
	$display("\n                                        lw test");
	instruction = 32'h8C01700f; //testing for lw
	regA = 32'h00000100;
	regB = 32'h00000000;
	#100
	$display("\n                                        sw test");
	instruction = 32'hAC01700f; //testing for sw
	regA = 32'h00000100;
	regB = 32'h00000000;
	#100
    $stop;
  end

alu  u_add(
    .instruction( instruction ),
    .regA( regA ),
    .regB( regB ),
    .result( result ),
    .flags(flags)
);

endmodule

Assignment/Assignment 3/Assignment_3/test.vcd
$date
	Mon Nov 13 22:09:21 2023
$end
$version
	Icarus Verilog
$end
$timescale
	1ps
$end
$scope module test $end
$var wire 32 ! result [31:0] $end
$var wire 3 " flags [2:0] $end
$var reg 32 # instruction [31:0] $end
$var reg 32 $ regA [31:0] $end
$var reg 32 % regB [31:0] $end
$scope module u_add $end
$var wire 32 & instruction [31:0] $end
$var wire 32 ' regA [31:0] $end
$var wire 32 ( regB [31:0] $end
$var wire 32 ) result [31:0] $end
$var reg 3 * flags [2:0] $end
$var reg 6 + func [5:0] $end
$var reg 16 , imm [15:0] $end
$var reg 6 - opcode [5:0] $end
$var reg 32 . rd [31:0] $end
$var reg 32 / rs [31:0] $end
$var reg 32 0 rt [31:0] $end
$var reg 6 1 shamt [5:0] $end
$var reg 32 2 temp [31:0] $end
$var reg 32 3 tempA [31:0] $end
$var reg 32 4 tempB [31:0] $end
$upscope $end
$upscope $end
$enddefinitions $end
#0
$dumpvars
b0 4
b0 3
b0 2
b0 1
b0 0
bx /
b0 .
b0 -
bx ,
b0 +
b0 *
b0 )
b0 (
b0 '
b0 &
b0 %
b0 $
b0 #
b0 "
b0 !
$end
#500000
b1 "
b1 *
b10000000000000000000000000000101 !
b10000000000000000000000000000101 )
b10000000000000000000000000000101 .
b1111111111111111111111111111111 0
b110 /
b1111111111111111111111111111111 2
b100000 +
b1111111111111111111111111111111 4
b110 3
b110 %
b110 (
b1111111111111111111111111111111 $
b1111111111111111111111111111111 '
b1000000000000000100000 #
b1000000000000000100000 &
#600000
b11 !
b11 )
b11 .
b10 0
b1 /
b0 "
b0 *
b10 4
b1 3
b10 %
b10 (
b1 $
b1 '
b10000000000100000 #
b10000000000100000 &
#700000
b1 "
b1 *
b10000000000000000000000000000000 !
b10000000000000000000000000000000 )
b10000000000000000000000000000000 .
b11111111111111111111111111111111 0
b1111111111111111111111111111111 /
b100010 +
b11111111111111111111111111111111 4
b1111111111111111111111111111111 3
b11111111111111111111111111111111 %
b11111111111111111111111111111111 (
b1111111111111111111111111111111 $
b1111111111111111111111111111111 '
b10000000000100010 #
b10000000000100010 &
#800000
b1 !
b1 )
b1 .
b11 0
b100 /
b0 "
b0 *
b11 4
b100 3
b11 %
b11 (
b100 $
b100 '
#900000
b10000000000000000000000000000101 !
b10000000000000000000000000000101 )
b10000000000000000000000000000101 .
b1111111111111111111111111111111 0
b110 /
b100001 +
b1111111111111111111111111111111 4
b110 3
b110 %
b110 (
b1111111111111111111111111111111 $
b1111111111111111111111111111111 '
b1000000000000000100001 #
b1000000000000000100001 &
#1000000
b10000000000000000000000000000000 !
b10000000000000000000000000000000 )
b10000000000000000000000000000000 .
b11111111111111111111111111111111 0
b1111111111111111111111111111111 /
b100011 +
b11111111111111111111111111111111 4
b1111111111111111111111111111111 3
b11111111111111111111111111111111 %
b11111111111111111111111111111111 (
b10000000000100011 #
b10000000000100011 &
#1100000
b1 !
b1 )
b1 .
b1 0
b11111111111111111111111111111111 /
b100100 +
b1 4
b11111111111111111111111111111111 3
b1 %
b1 (
b11111111111111111111111111111111 $
b11111111111111111111111111111111 '
b10000000000100100 #
b10000000000100100 &
#1200000
b0 0
b1 /
b0 4
b0 2
b100101 +
b1 3
b0 $
b0 '
b1000000000000000100101 #
b1000000000000000100101 &
#1300000
b11111111111111111111111111110000 !
b11111111111111111111111111110000 )
b11111111111111111111111111110000 .
b11111111111111111111111111111111 0
b1111 /
b11111111111111111111111111111111 2
b100110 +
b11111111111111111111111111111111 4
b1111 3
b1111 %
b1111 (
b11111111111111111111111111111111 $
b11111111111111111111111111111111 '
b1000000000000000100110 #
b1000000000000000100110 &
#1400000
b0 !
b0 )
b0 .
b0 0
b11111111111111111111111111111111 /
b0 4
b0 2
b100111 +
b11111111111111111111111111111111 3
b11111111111111111111111111111111 %
b11111111111111111111111111111111 (
b0 $
b0 '
b1000000000000000100111 #
b1000000000000000100111 &
#1500000
b10 "
b10 *
b11111111111111111111111111111111 !
b11111111111111111111111111111111 )
b11111111111111111111111111111111 .
b1 0
b0 /
b101010 +
b1 4
b0 3
b1 %
b1 (
b10000000000101010 #
b10000000000101010 &
#1600000
b1 !
b1 )
b1 .
b0 0
b1 /
b0 "
b0 *
b0 4
b1 3
b0 %
b0 (
b1 $
b1 '
#1700000
b10 "
b10 *
b11111111111111111111111111111111 0
b0 /
b101011 +
b11111111111111111111111111111111 4
b0 3
b11111111111111111111111111111111 %
b11111111111111111111111111111111 (
b0 $
b0 '
b10000000000101011 #
b10000000000101011 &
#1800000
b11111111111111111111111111111110 0
b11111111111111111111111111111111 /
b0 "
b0 *
b11111111111111111111111111111110 4
b11111111111111111111111111111111 3
b11111111111111111111111111111110 %
b11111111111111111111111111111110 (
b11111111111111111111111111111111 $
b11111111111111111111111111111111 '
#1900000
b10000000000 !
b10000000000 )
b10000000000 .
b1010 1
b1 0
b0 +
b1 4
b0 3
b1 %
b1 (
b0 $
b0 '
b10000001010000000 #
b10000001010000000 &
#2000000
b1111000000000000000000 !
b1111000000000000000000 )
b1111000000000000000000 .
b11110000000000000000000000000000 0
b10 +
b11110000000000000000000000000000 4
b11110000000000000000000000000000 %
b11110000000000000000000000000000 (
b10000001010000010 #
b10000001010000010 &
#2100000
b10000000000000000 !
b10000000000000000 )
b10000000000000000 .
b1 0
b10000 /
b100 +
b1 4
b10000 3
b1 %
b1 (
b10000 $
b10000 '
b10000000000000100 #
b10000000000000100 &
#2200000
b10000 !
b10000 )
b10000 .
b100000000 0
b100 /
b110 +
b100000000 4
b100 3
b100000000 %
b100000000 (
b100 $
b100 '
b10000000000000110 #
b10000000000000110 &
#2300000
b10000000 !
b10000000 )
b10000000 .
b1 /
b111 +
b1 3
b1 $
b1 '
b10000000000000111 #
b10000000000000111 &
#2400000
b100000000000000000000000000 !
b100000000000000000000000000 )
b100000000000000000000000000 .
b10 1
b10000000000000000000000000000 0
b11 +
b10000000000000000000000000000 4
b0 3
b10000000000000000000000000000 %
b10000000000000000000000000000 (
b0 $
b0 '
b10000000010000011 #
b10000000010000011 &
#2500000
b1 !
b1 )
b1 .
b1 ,
b0 /
b1 2
b1 +
b1000 -
b1 4
b0 3
b0 %
b0 (
b1 $
b1 '
b100000001000000000000000000001 #
b100000001000000000000000000001 &
#2600000
b100000000 !
b100000000 )
b100000000 .
b100000001 ,
b11111111111111111111111111111111 /
b11111111111111111111111111111111 2
b11111111111111111111111111111111 4
b11111111111111111111111111111111 3
b11111111111111111111111111111111 %
b11111111111111111111111111111111 (
b11111111111111111111111111111111 $
b11111111111111111111111111111111 '
b100000001000000000000100000001 #
b100000001000000000000100000001 &
#2700000
b1 !
b1 )
b1 .
b1 ,
b1100 -
b0 4
b0 %
b0 (
b110000000000010000000000000001 #
b110000000000010000000000000001 &
#2800000
b11000000000000010 !
b11000000000000010 )
b11000000000000010 .
b1000000000000001 ,
b1 /
b1000 -
b1 3
b1 $
b1 '
b100010000000011000000000000001 #
b100010000000011000000000000001 &
#2900000
b0 !
b0 )
b0 .
b1 ,
b10000 /
b1100 -
b10000 3
b10000 $
b10000 '
b110010000000010000000000000001 #
b110010000000010000000000000001 &
#3000000
b1 /
b1110 -
b1 3
b1 $
b1 '
b111000000000010000000000000001 #
b111000000000010000000000000001 &
#3100000
b10 "
b10 *
b11111111111111111111111111111111 !
b11111111111111111111111111111111 )
b11111111111111111111111111111111 .
b0 /
b1010 -
b0 3
b0 $
b0 '
b101000000000010000000000000001 #
b101000000000010000000000000001 &
#3200000
b1 !
b1 )
b1 .
b0 ,
b1 /
b0 "
b0 *
b0 +
b1 3
b1 $
b1 '
b101000000000010000000000000000 #
b101000000000010000000000000000 &
#3300000
b100 "
b100 *
b0 !
b0 )
b0 .
b1 0
b1 +
b100 -
b1 4
b1 %
b1 (
b10000000000010000000000000001 #
b10000000000010000000000000001 &
#3400000
b11111111111111111111111111111111 !
b11111111111111111111111111111111 )
b11111111111111111111111111111111 .
b0 /
b0 "
b0 *
b0 3
b0 $
b0 '
#3500000
b1 !
b1 )
b1 .
b0 0
b1 /
b101 -
b0 4
b1 3
b0 %
b0 (
b1 $
b1 '
b10100000000010000000000000001 #
b10100000000010000000000000001 &
#3600000
b100 "
b100 *
b0 !
b0 )
b0 .
b1 0
b1 4
b1 %
b1 (
#3700000
b11111111111111111111111111110001 !
b11111111111111111111111111110001 )
b11111111111111111111111111110001 .
b10000 ,
b10 "
b10 *
b10000 +
b1011 -
b0 4
b0 %
b0 (
b101100000000010000000000010000 #
b101100000000010000000000010000 &
#3800000
b11110000 !
b11110000 )
b11110000 .
b100000000 /
b0 "
b0 *
b100000000 3
b100000000 $
b100000000 '
#3900000
b111000100001111 !
b111000100001111 )
b111000100001111 .
b111000000001111 ,
b1111 +
b100011 -
b10001100000000010111000000001111 #
b10001100000000010111000000001111 &
#4000000
b101011 -
b10101100000000010111000000001111 #
b10101100000000010111000000001111 &
