Assignment/Assignment 3/temp/alu.v
// flags[2] : zero flag
// flags[1] : negative flag
// flags[0] : overflow flag 

// regA: 00000; regB: 00001

module alu(
    input [31:0] instruction,
    input [31:0] regA,
    input [31:0] regB,
    output reg [31:0] result,
    output reg [2:0] flags
);

    wire [5:0] opcode;
    reg [5:0] funct;
    reg [4:0] rs, rt, rd, shamt;
    reg [15:0] immediate;
    reg [31:0] rs_reg, rt_reg;

    reg [31:0] temp_reg;  // sign-extended immediate

    assign opcode = instruction[31:26];

    // parse instruction
    always @( * ) begin
        // R-type
        if (opcode == 6'b0) begin
            rs = instruction[25:21];
            rt = instruction[20:16];
            rd = instruction[15:11];
            shamt = instruction[10:6];
            funct = instruction[5:0];
        end
            // I-type
        else begin
            rs = instruction[25:21];
            rt = instruction[20:16];
            immediate = instruction[15:0];
        end
    end

    // fetch register values
    // we only have 00000 and 00001
    always @( * ) begin
        if (rs == 5'b0)
            rs_reg = regA;
        else
            rs_reg = regB;
        if (rt == 5'b0)
            rt_reg = regA;
        else
            rt_reg = regB;
    end

    // execute different instructions
    always @( * ) begin
        flags = 3'b0;  // default the flag
        result = 32'b0;  // default the result registers
        case (opcode)
            // R-type
            6'h00: begin
                case (funct)
                    6'h20: begin  // add
                        result = rs_reg + rt_reg;
                        if ({result[31], rs_reg[31], rt_reg[31]} == {3'b011} || {result[31], rs_reg[31], rt_reg[31]} ==
                       {3'b100})
                            flags[0] = 1'b1;
                    end
                    6'h21:  // addu
                        result = rs_reg + rt_reg;
                    6'h24:  // and
                        result = rs_reg & rt_reg;
                    6'h27:  // nor
                        result = ~ (rs_reg | rt_reg);
                    6'h25:  // or
                        result = rs_reg | rt_reg;
                    6'h00:  // sll
                        result = rt_reg << shamt;
                    6'h04:  // sllv
                        result = rt_reg << rs_reg;
                    6'h2A: begin  // slt
                        if (rs_reg[31] == 1 && rt_reg[31] == 0) begin
                            flags[1] = 1'b1;
                            result = 32'b1;
                        end
                        else if (rs_reg[31] == 0 && rt_reg[31] == 1) begin
                            flags[1] = 1'b0;
                            result = 32'b0;
                        end
                        else if ($signed(rs_reg - rt_reg) < 0) begin
                            flags[1] = 1'b1;
                            result = 32'b1;
                        end
                        else begin
                            flags[1] = 1'b0;
                            result = 32'b0;
                        end
                    end
                    6'h2B: begin  // sltu
                        if (rs_reg < rt_reg) begin
                            flags[1] = 1'b1;
                            result = 32'b1;
                        end
                        else begin
                            flags[1] = 1'b0;
                            result = 32'b0;
                        end
                    end
                    6'h03:  // sra
                        result = $signed(rt_reg) >>> shamt;
                    6'h07:  // srav
                        result = $signed(rt_reg) >>> rs_reg;
                    6'h02:  // srl
                        result = rt_reg >> shamt;
                    6'h06:  // srlv
                        result = rt_reg >> rs_reg;
                    6'h22: begin  // sub
                        result = rs_reg - rt_reg;
                        if ({result[31], rs_reg[31], rt_reg[31]} == {3'b101} || {result[31], rs_reg[31], rt_reg[31]} ==
                       {3'b010})
                            flags[0] = 1;
                    end
                    6'h23:  // subu
                        result = rs_reg - rt_reg;
                    6'h26:  // xor
                        result = rs_reg ^ rt_reg;
                endcase
            end

            // I-type
            6'h08: begin  // addi
                temp_reg = $signed(immediate);
                result = rs_reg + temp_reg;
                if ({result[31], immediate[15], rs_reg[31]} == {3'b100} || {result[31], immediate[15], rs_reg[31]} == {
                       3'b011})
                    flags[0] = 1;
            end
            6'h09: begin  // addiu
                temp_reg = $signed(immediate);
                result = rs_reg + temp_reg;
            end
            6'h0C:  // andi
                result = rs_reg & {16'b0, immediate};
            6'h04: begin  // beq
                result = rs_reg - rt_reg;
                if (result == 32'b0)
                    flags[2] = 1'b1;
                else
                    flags[2] = 1'b0;
            end
            6'h05: begin  // bne
                result = rs_reg - rt_reg;
                if (result == 32'b0)
                    flags[2] = 1'b1;
                else
                    flags[2] = 1'b0;
            end
            6'h23: begin  // lw
                temp_reg = $signed(immediate);
                result = rs_reg + temp_reg;
            end
            6'h0D:  // ori
                result = rs_reg | {16'b0, immediate};
            6'h0A: begin  // slti
                temp_reg = $signed(immediate);
                if (rs_reg[31] == 1 && temp_reg[31] == 0) begin
                    flags[1] = 1'b1;
                    result = 32'b1;
                end
                else if (rs_reg[31] == 0 && temp_reg[31] == 1) begin
                    flags[1] = 1'b0;
                    result = 32'b0;
                end
                else if ($signed(rs_reg - temp_reg) < 0) begin
                    flags[1] = 1'b1;
                    result = 32'b1;
                end
                else begin
                    flags[1] = 1'b0;
                    result = 32'b0;
                end
            end
            6'h0B: begin  // sltiu
                temp_reg = $signed(immediate);
                if (rs_reg < temp_reg) begin
                    flags[1] = 1'b1;
                    result = 32'b1;
                end
                else begin
                    flags[1] = 1'b0;
                    result = 32'b0;
                end
            end
            6'h2B: begin  // sw
                temp_reg = $signed(immediate);
                result = rs_reg + temp_reg;
            end
            6'h0E:  // xori
                result = rs_reg ^ {16'b0, immediate};
        endcase
    end
endmodule

Assignment/Assignment 3/temp/test_alu.v
`timescale 1ns/1ps

module test();
reg  [31:0] instruction;
reg  [31:0] regA;
reg  [31:0] regB;
wire [31:0] result;
wire [2:0] flags;

  initial begin
    $dumpfile("test.vcd");
    $dumpvars;
  end

  initial begin
	$display("\n                                   initialize");
	$monitor("instruction = 32'h%h, regA = 32'h%h, regB = 32'h%h, result = 32'h%h, flags = 3'b%b",instruction,regA,regB,result,flags);
        instruction = 32'b0;
        regA = 32'b0; 
        regB = 32'b0;
        #500
	$display("\n                                   for R Type");
	$display("\n                                   format is");
	$display("\n                      instruction:regA:regB:result:flags");
	$display("\n                                add overflow test");
        instruction = 32'h00200020;   // testing for add overflow
        regA = 32'h7FFFFFFF;
        regB = 32'h00000006;
        #100
	$display("\n                                add normal test");
	instruction = 32'h00010020;   // testing for add normal
	regA = 32'h00000001;
	regB = 32'h00000002;
	#100
	$display("\n                                sub overflow test");
        instruction = 32'h00010022;   // testing for sub overflow
        regA = 32'h7FFFFFFF;
        regB = 32'hFFFFFFFF;
	#100
	$display("\n                                sub normal test");
	instruction = 32'h00010022;   // testing for sub normal
	regA = 32'h00000004;
	regB = 32'h00000003;
	#100
	$display("\n                                  addu test");
	instruction = 32'h00200021;   // testing for addu 
	regA = 32'h7FFFFFFF;
	regB = 32'h00000006;
	#100 
	$display("\n                                  subu test");
	instruction = 32'h00010023;   // testing for subu
	regA = 32'h7FFFFFFF;
	regB = 32'hFFFFFFFF;
	#100
	$display("\n                                  and test");
	instruction = 32'h00010024;   // testing for and
	regA = 32'hFFFFFFFF;
	regB = 32'h00000001;
	#100
	$display("\n                                   or test");
	instruction = 32'h00200025;   // testing for or
	regA = 32'h00000000;
	regB = 32'h00000001;
	#100
	$display("\n                                  xor test");
	instruction = 32'h00200026;  // testing for xor
	regA = 32'hFFFFFFFF;
	regB = 32'h0000000F;
	#100
	$display("\n                                  nor test");
	instruction = 32'h00200027;  //testing for nor
	regA = 32'h00000000;
	regB = 32'hFFFFFFFF;
	#100
	$display("\n                             slt test(negative)");
	instruction = 32'h0001002A;  // testing for slt
	regA = 32'h00000000;
	regB = 32'h00000001;
	#100
	$display("\n                          slt test(non-negative)");
	instruction = 32'h0001002A;
	regA = 32'h00000001;
	regB = 32'h00000000;
	#100
	$display("\n                           sltu test(negative)");
	instruction = 32'h0001002B;  // testing for sltu
	regA = 32'h00000000;
	regB = 32'hFFFFFFFF;
	#100
	$display("\n                                sltu test");
	instruction = 32'h0001002B;  // testing for sltu
	regA = 32'hFFFFFFFF;
	regB = 32'hFFFFFFFE;
	#100
	$display("\n                                sll test");
	instruction = 32'h00010280;  // testing for sll (10)
	regA = 32'h00000000;
	regB = 32'h00000001;
	#100
	$display("\n                                srl test");
	instruction = 32'h00010282;  //testing for srl(10)
	regA = 32'h00000000;
	regB = 32'hF0000000;
	#100
        $display("\n                                sllv test");
	instruction = 32'h00010004; //testing for sllv
	regA = 32'h00000010;
	regB = 32'h00000001;
	#100
	$display("\n                                srlv test");
	instruction = 32'h00010006; // testing for srlv
	regA = 32'h00000004;
	regB = 32'h00000100;
	#100
	$display("\n                                srav test");
	instruction = 32'h00010007; // testing for srav
	regA = 32'h00000001;
	regB = 32'h00000100;
	#100
	$display("\n                                sra test");
	instruction = 32'h00010083; // testing for sra
	regA = 32'h00000000;
	regB = 32'h10000000;
	#100
	$display("\n                                         for I Type");
	$display("\n                                         format is");
	$display("\n                        instruction:regA:regB:immediate:result:flags");
	$monitor("instruction = 32'h%h, regA = 32'h%h, regB = 32'h%h, immediate = 16'b%b, result = 32'h%h, flags = 3'b%b",instruction,regA,regB,instruction[15:0],result,flags);
	$display("\n                                         addi test");
	instruction = 32'h20200001;  // testing for addi
	regA = 32'h00000001;
	regB = 32'h00000000;
	#100
	$display("\n                                     addi test(overflow)");
	instruction = 32'h20200101;  // testing for addi
	regA = 32'hFFFFFFFF;
	regB = 32'hFFFFFFFF;
	#100
	$display("\n                                        andi test");
	instruction = 32'h30010001;  // testing for andi
	regA = 32'hFFFFFFFF;
	regB = 32'h00000000;
	#100
	$display("\n                                        addiu test");
	instruction = 32'h22018001;  //testing for addiu
	regA = 32'h00000001;
	regB = 32'h00000000;
	#100
	$display("\n                                         ori test");
	instruction = 32'h32010001; //testing for ori
	regA = 32'h00000010;
	regB = 32'h00000000;
	#100
	$display("\n                                        xori test");
	instruction = 32'h38010001; //testing for xori
	regA = 32'h00000001;
	regB = 32'h00000000;
	#100
	$display("\n                                   slti test(negative)");
	instruction = 32'h28010001; //testing for slti
	regA = 32'h00000000;
	regB = 32'h00000000;
	#100
	$display("\n                                        slti test");
	instruction = 32'h28010000; //testing for slti
	regA = 32'h00000001;
	regB = 32'h00000000;
	#100
	$display("\n                                     beq test(zero)");
	instruction = 32'h10010001; //testing for beq
	regA = 32'h00000001;
	regB = 32'h00000001;
	#100
	$display("\n                                   beq test(non-zero)");
	instruction = 32'h10010001; //testing for beq
	regA = 32'h00000000;
	regB = 32'h00000001;
	#100
	$display("\n                                   bne test(non-zero)");
	instruction = 32'h14010001; //testing for bne
	regA = 32'h00000001;
	regB = 32'h00000000;
	#100
	$display("\n                                     bne test(zero)");
	instruction = 32'h14010001; //testing for bne
	regA = 32'h00000001;
	regB = 32'h00000001;
	#100
	$display("\n                                  sltiu test(negative)");
	instruction = 32'h2C010010; //testing for sltiu
	regA = 32'h00000001;
	regB = 32'h00000000;
	#100
	$display("\n                                sltiu test(non-negative)");
	instruction = 32'h2C010010; //testing for sltiu
	regA = 32'h00000100;
	regB = 32'h00000000;
	#100
	$display("\n                                        lw test");
	instruction = 32'h8C01700f; //testing for lw
	regA = 32'h00000100;
	regB = 32'h00000000;
	#100
	$display("\n                                        sw test");
	instruction = 32'hAC01700f; //testing for sw
	regA = 32'h00000100;
	regB = 32'h00000000;
	#100
    $stop;
  end

alu  u_add(
    .instruction( instruction ),
    .regA( regA ),
    .regB( regB ),
    .result( result ),
    .flags(flags)
);

endmodule

Assignment/Assignment 3/temp/test.vcd
$date
	Fri Nov 17 10:29:59 2023
$end
$version
	Icarus Verilog
$end
$timescale
	1ps
$end
$scope module test $end
$var wire 32 ! result [31:0] $end
$var wire 3 " flags [2:0] $end
$var reg 32 # instruction [31:0] $end
$var reg 32 $ regA [31:0] $end
$var reg 32 % regB [31:0] $end
$scope module u_add $end
$var wire 32 & instruction [31:0] $end
$var wire 32 ' regA [31:0] $end
$var wire 32 ( regB [31:0] $end
$var wire 6 ) opcode [5:0] $end
$var reg 3 * flags [2:0] $end
$var reg 6 + funct [5:0] $end
$var reg 16 , immediate [15:0] $end
$var reg 5 - rd [4:0] $end
$var reg 32 . result [31:0] $end
$var reg 5 / rs [4:0] $end
$var reg 32 0 rs_reg [31:0] $end
$var reg 5 1 rt [4:0] $end
$var reg 32 2 rt_reg [31:0] $end
$var reg 5 3 shamt [4:0] $end
$var reg 32 4 temp_reg [31:0] $end
$upscope $end
$upscope $end
$enddefinitions $end
#0
$dumpvars
bx 4
b0 3
b0 2
b0 1
b0 0
b0 /
b0 .
b0 -
bx ,
b0 +
b0 *
b0 )
b0 (
b0 '
b0 &
b0 %
b0 $
b0 #
b0 "
b0 !
$end
#500000
b1 "
b1 *
b10000000000000000000000000000101 !
b10000000000000000000000000000101 .
b1111111111111111111111111111111 2
b110 0
b100000 +
b1 /
b110 %
b110 (
b1111111111111111111111111111111 $
b1111111111111111111111111111111 '
b1000000000000000100000 #
b1000000000000000100000 &
#600000
b11 !
b11 .
b0 "
b0 *
b10 2
b1 0
b1 1
b0 /
b10 %
b10 (
b1 $
b1 '
b10000000000100000 #
b10000000000100000 &
#700000
b1 "
b1 *
b10000000000000000000000000000000 !
b10000000000000000000000000000000 .
b11111111111111111111111111111111 2
b1111111111111111111111111111111 0
b100010 +
b11111111111111111111111111111111 %
b11111111111111111111111111111111 (
b1111111111111111111111111111111 $
b1111111111111111111111111111111 '
b10000000000100010 #
b10000000000100010 &
#800000
b1 !
b1 .
b0 "
b0 *
b11 2
b100 0
b11 %
b11 (
b100 $
b100 '
#900000
b10000000000000000000000000000101 !
b10000000000000000000000000000101 .
b1111111111111111111111111111111 2
b110 0
b100001 +
b0 1
b1 /
b110 %
b110 (
b1111111111111111111111111111111 $
b1111111111111111111111111111111 '
b1000000000000000100001 #
b1000000000000000100001 &
#1000000
b10000000000000000000000000000000 !
b10000000000000000000000000000000 .
b11111111111111111111111111111111 2
b1111111111111111111111111111111 0
b100011 +
b1 1
b0 /
b11111111111111111111111111111111 %
b11111111111111111111111111111111 (
b10000000000100011 #
b10000000000100011 &
#1100000
b1 !
b1 .
b1 2
b11111111111111111111111111111111 0
b100100 +
b1 %
b1 (
b11111111111111111111111111111111 $
b11111111111111111111111111111111 '
b10000000000100100 #
b10000000000100100 &
#1200000
b1 !
b1 .
b0 2
b1 0
b100101 +
b0 1
b1 /
b0 $
b0 '
b1000000000000000100101 #
b1000000000000000100101 &
#1300000
b11111111111111111111111111110000 !
b11111111111111111111111111110000 .
b11111111111111111111111111111111 2
b1111 0
b100110 +
b1111 %
b1111 (
b11111111111111111111111111111111 $
b11111111111111111111111111111111 '
b1000000000000000100110 #
b1000000000000000100110 &
#1400000
b0 !
b0 .
b0 2
b11111111111111111111111111111111 0
b100111 +
b11111111111111111111111111111111 %
b11111111111111111111111111111111 (
b0 $
b0 '
b1000000000000000100111 #
b1000000000000000100111 &
#1500000
b1 !
b1 .
b10 "
b10 *
b1 2
b0 0
b101010 +
b1 1
b0 /
b1 %
b1 (
b10000000000101010 #
b10000000000101010 &
#1600000
b0 !
b0 .
b0 "
b0 *
b0 2
b1 0
b0 %
b0 (
b1 $
b1 '
#1700000
b1 !
b1 .
b10 "
b10 *
b11111111111111111111111111111111 2
b0 0
b101011 +
b11111111111111111111111111111111 %
b11111111111111111111111111111111 (
b0 $
b0 '
b10000000000101011 #
b10000000000101011 &
#1800000
b0 !
b0 .
b0 "
b0 *
b11111111111111111111111111111110 2
b11111111111111111111111111111111 0
b11111111111111111111111111111110 %
b11111111111111111111111111111110 (
b11111111111111111111111111111111 $
b11111111111111111111111111111111 '
#1900000
b10000000000 !
b10000000000 .
b1 2
b0 0
b0 +
b1010 3
b1 %
b1 (
b0 $
b0 '
b10000001010000000 #
b10000001010000000 &
#2000000
b1111000000000000000000 !
b1111000000000000000000 .
b11110000000000000000000000000000 2
b10 +
b11110000000000000000000000000000 %
b11110000000000000000000000000000 (
b10000001010000010 #
b10000001010000010 &
#2100000
b10000000000000000 !
b10000000000000000 .
b1 2
b10000 0
b100 +
b0 3
b1 %
b1 (
b10000 $
b10000 '
b10000000000000100 #
b10000000000000100 &
#2200000
b10000 !
b10000 .
b100000000 2
b100 0
b110 +
b100000000 %
b100000000 (
b100 $
b100 '
b10000000000000110 #
b10000000000000110 &
#2300000
b10000000 !
b10000000 .
b1 0
b111 +
b1 $
b1 '
b10000000000000111 #
b10000000000000111 &
#2400000
b100000000000000000000000000 !
b100000000000000000000000000 .
b10000000000000000000000000000 2
b0 0
b11 +
b10 3
b10000000000000000000000000000 %
b10000000000000000000000000000 (
b0 $
b0 '
b10000000010000011 #
b10000000010000011 &
#2500000
b1 4
b1 !
b1 .
b1 2
b1 ,
b0 1
b1 /
b1000 )
b0 %
b0 (
b1 $
b1 '
b100000001000000000000000000001 #
b100000001000000000000000000001 &
#2600000
b100000001 4
b100000000 !
b100000000 .
b11111111111111111111111111111111 2
b11111111111111111111111111111111 0
b100000001 ,
b11111111111111111111111111111111 %
b11111111111111111111111111111111 (
b11111111111111111111111111111111 $
b11111111111111111111111111111111 '
b100000001000000000000100000001 #
b100000001000000000000100000001 &
#2700000
b1 !
b1 .
b0 2
b1 ,
b1 1
b0 /
b1100 )
b0 %
b0 (
b110000000000010000000000000001 #
b110000000000010000000000000001 &
#2800000
b11111111111111111000000000000001 4
b11111111111111111000000000000001 !
b11111111111111111000000000000001 .
b0 0
b1000000000000001 ,
b10000 /
b1000 )
b1 $
b1 '
b100010000000011000000000000001 #
b100010000000011000000000000001 &
#2900000
b0 !
b0 .
b1 ,
b1100 )
b10000 $
b10000 '
b110010000000010000000000000001 #
b110010000000010000000000000001 &
#3000000
b1 0
b0 /
b1110 )
b1 $
b1 '
b111000000000010000000000000001 #
b111000000000010000000000000001 &
#3100000
b1 !
b1 .
b10 "
b10 *
b1 4
b0 0
b1010 )
b0 $
b0 '
b101000000000010000000000000001 #
b101000000000010000000000000001 &
#3200000
b0 4
b0 !
b0 .
b0 "
b0 *
b1 0
b0 ,
b1 $
b1 '
b101000000000010000000000000000 #
b101000000000010000000000000000 &
#3300000
b100 "
b100 *
b1 2
b1 ,
b100 )
b1 %
b1 (
b10000000000010000000000000001 #
b10000000000010000000000000001 &
#3400000
b11111111111111111111111111111111 !
b11111111111111111111111111111111 .
b0 "
b0 *
b0 0
b0 $
b0 '
#3500000
b1 !
b1 .
b0 2
b1 0
b101 )
b0 %
b0 (
b1 $
b1 '
b10100000000010000000000000001 #
b10100000000010000000000000001 &
#3600000
b100 "
b100 *
b0 !
b0 .
b1 2
b1 %
b1 (
#3700000
b1 !
b1 .
b10000 4
b10 "
b10 *
b0 2
b10000 ,
b1011 )
b0 %
b0 (
b101100000000010000000000010000 #
b101100000000010000000000010000 &
#3800000
b0 !
b0 .
b0 "
b0 *
b100000000 0
b100000000 $
b100000000 '
#3900000
b111000100001111 !
b111000100001111 .
b111000000001111 4
b111000000001111 ,
b100011 )
b10001100000000010111000000001111 #
b10001100000000010111000000001111 &
#4000000
b111000100001111 !
b111000100001111 .
b101011 )
b10101100000000010111000000001111 #
b10101100000000010111000000001111 &
